{
	"close":false,
	"natures":["egretProject"],
	"resourcePlugin":{
		"configs":[{
				"configPath":"resource/default.res.json",
				"relativePath":"resource/"
			}],
		"id":"org.egret-labs.resource",
		"library":{
			"children":[
				{
					"isFolder":false,
					"key":"load_anim0_png",
					"name":"load_anim0_png"
				},
				{
					"isFolder":false,
					"key":"load_anim1_png",
					"name":"load_anim1_png"
				},
				{
					"isFolder":false,
					"key":"load_anim2_png",
					"name":"load_anim2_png"
				},
				{
					"isFolder":false,
					"key":"load_anim3_png",
					"name":"load_anim3_png"
				},
				{
					"isFolder":false,
					"key":"load_bar_png",
					"name":"load_bar_png"
				},
				{
					"isFolder":false,
					"key":"load_barbg_png",
					"name":"load_barbg_png"
				},
				{
					"isFolder":false,
					"key":"load_bg_png",
					"name":"load_bg_png"
				},
				{
					"isFolder":false,
					"key":"game_arrow_png",
					"name":"game_arrow_png"
				},
				{
					"isFolder":false,
					"key":"game_bg_png",
					"name":"game_bg_png"
				},
				{
					"isFolder":false,
					"key":"game_fall_png",
					"name":"game_fall_png"
				},
				{
					"isFolder":false,
					"key":"game_hand_png",
					"name":"game_hand_png"
				},
				{
					"isFolder":false,
					"key":"game_item0_png",
					"name":"game_item0_png"
				},
				{
					"isFolder":false,
					"key":"game_item1_png",
					"name":"game_item1_png"
				},
				{
					"isFolder":false,
					"key":"game_item2_png",
					"name":"game_item2_png"
				},
				{
					"isFolder":false,
					"key":"game_packet_png",
					"name":"game_packet_png"
				},
				{
					"isFolder":false,
					"key":"game_moneybg_png",
					"name":"game_moneybg_png"
				},
				{
					"isFolder":false,
					"key":"game_timebg_png",
					"name":"game_timebg_png"
				},
				{
					"isFolder":false,
					"key":"game_bag_png",
					"name":"game_bag_png"
				},
				{
					"isFolder":false,
					"key":"game_resultbg_png",
					"name":"game_resultbg_png"
				},
				{
					"isFolder":false,
					"key":"share0_png",
					"name":"share0_png"
				},
				{
					"isFolder":false,
					"key":"share1_png",
					"name":"share1_png"
				},
				{
					"isFolder":false,
					"key":"open_bg_png",
					"name":"open_bg_png"
				},
				{
					"isFolder":false,
					"key":"open_open_png",
					"name":"open_open_png"
				},
				{
					"isFolder":false,
					"key":"rule_bg_png",
					"name":"rule_bg_png"
				},
				{
					"isFolder":false,
					"key":"rule_btn_png",
					"name":"rule_btn_png"
				},
				{
					"isFolder":false,
					"key":"rule_content_png",
					"name":"rule_content_png"
				},
				{
					"isFolder":false,
					"key":"roundthumb_png",
					"name":"roundthumb_png"
				},
				{
					"isFolder":false,
					"key":"open_opened.png_png",
					"name":"open_opened.png_png"
				},
				{
					"isFolder":false,
					"key":"open_opened2.png_png",
					"name":"open_opened2.png_png"
				},
				{
					"isFolder":false,
					"key":"prize_phone_png",
					"name":"prize_phone_png"
				},
				{
					"isFolder":false,
					"key":"prize_result_png",
					"name":"prize_result_png"
				},
				{
					"isFolder":false,
					"key":"prize1_png",
					"name":"prize1_png"
				},
				{
					"isFolder":false,
					"key":"prize2_png",
					"name":"prize2_png"
				},
				{
					"isFolder":false,
					"key":"prize3_png",
					"name":"prize3_png"
				},
				{
					"isFolder":false,
					"key":"prize4_png",
					"name":"prize4_png"
				},
				{
					"isFolder":false,
					"key":"prize5_png",
					"name":"prize5_png"
				},
				{
					"isFolder":false,
					"key":"prize6_png",
					"name":"prize6_png"
				},
				{
					"isFolder":false,
					"key":"prize7_png",
					"name":"prize7_png"
				},
				{
					"isFolder":false,
					"key":"count1_png",
					"name":"count1_png"
				},
				{
					"isFolder":false,
					"key":"count2_png",
					"name":"count2_png"
				},
				{
					"isFolder":false,
					"key":"count3_png",
					"name":"count3_png"
				},
				{
					"isFolder":false,
					"key":"count_rule_png",
					"name":"count_rule_png"
				}
			]
		}
	},
	"theme":"resource/default.thm.json",
	"tmRelativePath":"design/"
}